polar/__init__.py
polar/polar.py
polar/so3.py
polar/example/__init__.py
polar/example/data.pt
polar/example/utils.py
polar/network/__init__.py
polar/network/model.py
polar/network/weights/final.pt
polar/network/weights/final.toml
polar/train/__init__.py
polar/train/train.py
polar/train/data/__init__.py
polar/train/data/augmented_loader.py
polar/train/data/factory.py
polar/train/data/modelnet.py
polar/train/data/transforms/__init__.py
polar/train/data/transforms/core.py
polar/train/data/transforms/functionals.py
polar/train/data/transforms/transforms.py
polaregistration-0.1.1.dist-info/METADATA
polaregistration-0.1.1.dist-info/WHEEL
polaregistration-0.1.1.dist-info/top_level.txt
polaregistration-0.1.1.dist-info/RECORD
