Metadata-Version: 2.1
Name: polaregistration
Version: 0.1.1
Summary: POLAR package
Author-email: Luc Vedrenne <vedrenne@unistra.fr>
Project-URL: Repository, https://github.com/pypolar/polar.git
Classifier: Programming Language :: Python :: 3
Classifier: License :: OSI Approved :: MIT License
Classifier: Operating System :: OS Independent
Requires-Python: >=3.7
Requires-Dist: numpy
Requires-Dist: torch
Requires-Dist: torch-geometric
Requires-Dist: tqdm
Requires-Dist: typing-extensions ; python_version < "3.10"
Provides-Extra: all
Requires-Dist: polar[train] ; extra == 'all'
Requires-Dist: polar[vis] ; extra == 'all'
Provides-Extra: train
Requires-Dist: h5py ; extra == 'train'
Requires-Dist: toml ; extra == 'train'
Provides-Extra: viz
Requires-Dist: plotly ; extra == 'viz'
